sequana_pipetools/__init__.py
sequana_pipetools/info.py
sequana_pipetools/misc.py
sequana_pipetools/options.py
sequana_pipetools/resources/__init__.py
sequana_pipetools/resources/ext.py
sequana_pipetools/resources/local.yaml
sequana_pipetools/resources/slurm.yaml
sequana_pipetools/scripts/__init__.py
sequana_pipetools/scripts/main.py
sequana_pipetools/sequana_manager.py
sequana_pipetools/snaketools/__init__.py
sequana_pipetools/snaketools/dot_parser.py
sequana_pipetools/snaketools/errors.py
sequana_pipetools/snaketools/file_factory.py
sequana_pipetools/snaketools/module.py
sequana_pipetools/snaketools/module_finder.py
sequana_pipetools/snaketools/pipeline_manager.py
sequana_pipetools/snaketools/pipeline_utils.py
sequana_pipetools/snaketools/profile.py
sequana_pipetools/snaketools/sequana_config.py
sequana_pipetools/snaketools/slurm.py
sequana_pipetools-1.3.1.dist-info/METADATA
sequana_pipetools-1.3.1.dist-info/WHEEL
sequana_pipetools-1.3.1.dist-info/entry_points.txt
sequana_pipetools-1.3.1.dist-info/RECORD
