Metadata-Version: 2.4
Name: sequana_pipetools
Version: 1.3.1
Summary: A set of tools to help building or using Sequana pipelines
License: BSD-3
Keywords: snakemake,sequana,pipelines
Author: Sequana Team
Author-email: thomas.cokelaer@pasteur.fr
Requires-Python: >=3.8,<4.0
Classifier: Development Status :: 5 - Production/Stable
Classifier: Intended Audience :: Education
Classifier: Intended Audience :: End Users/Desktop
Classifier: Intended Audience :: Developers
Classifier: Intended Audience :: Science/Research
Classifier: License :: OSI Approved :: BSD License
Classifier: Operating System :: OS Independent
Classifier: Programming Language :: Python :: 3.9
Classifier: Programming Language :: Python :: 3.10
Classifier: Programming Language :: Python :: 3.11
Classifier: Programming Language :: Python :: 3.12
Classifier: Topic :: Software Development :: Libraries :: Python Modules
Classifier: Topic :: Scientific/Engineering :: Bio-Informatics
Classifier: Topic :: Scientific/Engineering :: Information Analysis
Requires-Dist: aiohttp (>=3.8.4)
Requires-Dist: charset-normalizer (>=2)
Requires-Dist: cookiecutter (>=2.6.0)
Requires-Dist: docutils (>0.20,!=0.21)
Requires-Dist: easydev (>=0.12)
Requires-Dist: importlib_resources (>=5.4.0)
Requires-Dist: packaging (>=23.1)
Requires-Dist: parse (>=1.19.0)
Requires-Dist: pykwalify (>=1.8)
Requires-Dist: pyyaml (>=1.3)
Requires-Dist: rich-click (>=1.7.1)
Requires-Dist: ruamel.yaml (>=0.18.5)
Requires-Dist: tqdm (>=4.65)
Requires-Dist: versionix (>=0.99.2,<0.100.0)
